beer_garden/__init__.py
beer_garden/__main__.py
beer_garden/__version__.py
beer_garden/app.py
beer_garden/authorization.py
beer_garden/commands.py
beer_garden/config.py
beer_garden/errors.py
beer_garden/files.py
beer_garden/garden.py
beer_garden/log.py
beer_garden/metrics.py
beer_garden/monitor.py
beer_garden/plugin.py
beer_garden/publish_request.py
beer_garden/queues.py
beer_garden/replication.py
beer_garden/requests.py
beer_garden/role.py
beer_garden/router.py
beer_garden/scheduler.py
beer_garden/systems.py
beer_garden/topic.py
beer_garden/user.py
beer_garden/api/__init__.py
beer_garden/api/entry_point.py
beer_garden/api/http/__init__.py
beer_garden/api/http/base_handler.py
beer_garden/api/http/client.py
beer_garden/api/http/exceptions.py
beer_garden/api/http/metrics.py
beer_garden/api/http/processors.py
beer_garden/api/http/authentication/__init__.py
beer_garden/api/http/authentication/login_handlers/__init__.py
beer_garden/api/http/authentication/login_handlers/base.py
beer_garden/api/http/authentication/login_handlers/basic.py
beer_garden/api/http/authentication/login_handlers/ldap.py
beer_garden/api/http/authentication/login_handlers/trusted_header.py
beer_garden/api/http/handlers/__init__.py
beer_garden/api/http/handlers/authorization_handler.py
beer_garden/api/http/handlers/misc.py
beer_garden/api/http/handlers/v1/__init__.py
beer_garden/api/http/handlers/v1/admin.py
beer_garden/api/http/handlers/v1/command.py
beer_garden/api/http/handlers/v1/event.py
beer_garden/api/http/handlers/v1/forward.py
beer_garden/api/http/handlers/v1/garden.py
beer_garden/api/http/handlers/v1/instance.py
beer_garden/api/http/handlers/v1/job.py
beer_garden/api/http/handlers/v1/logging.py
beer_garden/api/http/handlers/v1/queue.py
beer_garden/api/http/handlers/v1/request.py
beer_garden/api/http/handlers/v1/role.py
beer_garden/api/http/handlers/v1/system.py
beer_garden/api/http/handlers/v1/token.py
beer_garden/api/http/handlers/v1/topic.py
beer_garden/api/http/handlers/v1/user.py
beer_garden-3.31.1.dist-info/METADATA
beer_garden-3.31.1.dist-info/WHEEL
beer_garden-3.31.1.dist-info/entry_points.txt
beer_garden-3.31.1.dist-info/top_level.txt
beer_garden-3.31.1.dist-info/RECORD
