Metadata-Version: 2.4
Name: beer_garden
Version: 3.31.1
Summary: Beergarden Application
Home-page: https://beer-garden.io
Author: The Beer Garden Team
Author-email: beer@beer-garden.io
License: MIT
Keywords: beer beer-garden beergarden
Classifier: Development Status :: 4 - Beta
Classifier: Intended Audience :: Developers
Classifier: License :: OSI Approved :: MIT License
Classifier: Natural Language :: English
Classifier: Programming Language :: Python :: 3
Classifier: Programming Language :: Python :: 3.11
Classifier: Programming Language :: Python :: 3.12
Classifier: Programming Language :: Python :: 3.13
Classifier: Programming Language :: Python :: 3.14
Requires-Dist: brewtils>=3.31.1
Requires-Dist: apispec<7,>=6.7
Requires-Dist: apispec-webframeworks<2,>1
Requires-Dist: apscheduler<4
Requires-Dist: more-itertools<11
Requires-Dist: wrapt
Requires-Dist: elastic-apm
Requires-Dist: ldap3>=2.9.1
Requires-Dist: pyrabbit2<2
Requires-Dist: pyjwt>=2.4.0
Requires-Dist: passlib<1.8
Requires-Dist: prometheus-client<1
Requires-Dist: pyyaml<7
Requires-Dist: stomp.py<9,>=7
Requires-Dist: tornado<7
Requires-Dist: urllib3<3
Requires-Dist: watchdog<6.1
Requires-Dist: pymongo<4.11,>=4.9
Requires-Dist: mongoengine>=0.29.1
Requires-Dist: python-box<4
Requires-Dist: ruamel.yaml<0.18
Requires-Dist: yapconf<0.5
Requires-Dist: marshmallow<4.1,>=4.0
Dynamic: author
Dynamic: author-email
Dynamic: classifier
Dynamic: description
Dynamic: description-content-type
Dynamic: home-page
Dynamic: keywords
Dynamic: license
Dynamic: requires-dist
Dynamic: summary
